.bumpversion.cfg
.cookiecutterrc
.coveragerc
.editorconfig
.gitignore
.pre-commit-config.yaml
.readthedocs.yml
.travis.yml
AUTHORS.rst
CHANGELOG.rst
CONTRIBUTING.rst
LICENSE
README.rst
pyproject.toml
setup.cfg
setup.py
tox.ini
ci/bootstrap.py
ci/requirements.txt
ci/templates/.travis.yml
docs/authors.rst
docs/changelog.rst
docs/conf.py
docs/contributing.rst
docs/index.rst
docs/installation.rst
docs/readme.rst
docs/requirements.txt
docs/spelling_wordlist.txt
docs/usage.rst
docs/reference/index.rst
docs/reference/snyk_test.rst
src/snyk_test/Package.py
src/snyk_test/__init__.py
src/snyk_test/__main__.py
src/snyk_test/_version.py
src/snyk_test/cli.py
src/snyk_test/utils.py
src/snyk_test.egg-info/PKG-INFO
src/snyk_test.egg-info/SOURCES.txt
src/snyk_test.egg-info/dependency_links.txt
src/snyk_test.egg-info/entry_points.txt
src/snyk_test.egg-info/not-zip-safe
src/snyk_test.egg-info/requires.txt
src/snyk_test.egg-info/top_level.txt
src/snyk_test/tests/__init__.py
tests/test_snyk_test.py