Metadata-Version: 1.2
Name: snyk-test
Version: 0.0.2
Summary: A package that wraps pysnyk library for easier usage from cli interfaces
Home-page: https://github.com/avishayil/python-snyk-test
Author: Avishay Bar
Author-email: avishay.il@gmail.com
License: MIT
Project-URL: Documentation, https://python-snyk-test.readthedocs.io/
Project-URL: Changelog, https://python-snyk-test.readthedocs.io/en/latest/changelog.html
Project-URL: Issue Tracker, https://github.com/avishayil/python-snyk-test/issues
Platform: UNKNOWN
Classifier: Development Status :: 5 - Production/Stable
Classifier: Intended Audience :: Developers
Classifier: License :: OSI Approved :: MIT License
Classifier: Operating System :: Unix
Classifier: Operating System :: POSIX
Classifier: Operating System :: Microsoft :: Windows
Classifier: Programming Language :: Python
Classifier: Programming Language :: Python :: 3.7
Classifier: Programming Language :: Python :: 3.8
Classifier: Topic :: Utilities
Requires-Python: >=3.7
